{
  "aor": 0.0012594545454545454,
  "aqi": 0.0191861025,
  "bids_meta": {
    "dataset": "ds002776",
    "modality": "bold",
    "run_id": 7,
    "session_id": "04",
    "subject_id": "24",
    "task_id": "motorseq"
  },
  "dummy_trs": 0,
  "dvars_nstd": 69.22103177107068,
  "dvars_std": 1.0132985097722103,
  "dvars_vstd": 0.9911350710022773,
  "efc": 0.5316200744408531,
  "fber": 265.85345458984375,
  "fd_mean": 0.17769341290675142,
  "fd_num": 112,
  "fd_perc": 25.454545454545453,
  "fwhm_avg": 2.511101666666667,
  "fwhm_x": 2.40692,
  "fwhm_y": 2.59595,
  "fwhm_z": 2.530435,
  "gcor": 0.00908183,
  "gsr_x": 0.009857911616563797,
  "gsr_y": 0.03547220304608345,
  "provenance": {
    "md5sum": "9bfab94d145353075157e180b60bb3ca",
    "settings": {
      "fd_thres": 0.2,
      "testing": false
    },
    "software": "mriqc",
    "version": "23.0.1",
    "webapi_port": null,
    "webapi_url": "https://mriqc.nimh.nih.gov/api/v1"
  },
  "size_t": 440,
  "size_x": 104,
  "size_y": 104,
  "size_z": 44,
  "snr": 1.6668643717902916,
  "spacing_tr": 1.0,
  "spacing_x": 2.0,
  "spacing_y": 2.0,
  "spacing_z": 2.0,
  "summary_bg_k": 48.850647678861066,
  "summary_bg_mad": 4.585960745225308,
  "summary_bg_mean": 24.81632423400879,
  "summary_bg_median": 17.865907669067383,
  "summary_bg_n": 292608.0,
  "summary_bg_p05": 13.509090423583984,
  "summary_bg_p95": 60.47874736785881,
  "summary_bg_stdv": 24.020328521728516,
  "summary_fg_k": 4.078685818332034,
  "summary_fg_mad": 132.5311461474636,
  "summary_fg_mean": 337.33636474609375,
  "summary_fg_median": 291.8431701660156,
  "summary_fg_n": 114119.0,
  "summary_fg_p05": 155.3699981689453,
  "summary_fg_p95": 690.5179321289058,
  "summary_fg_stdv": 175.08436584472656,
  "tsnr": 16.026358457515016
}