{
  "aor": 0.00041429545454545457,
  "aqi": 0.01565979818181818,
  "bids_meta": {
    "dataset": "ds002776",
    "modality": "bold",
    "run_id": 8,
    "session_id": "03",
    "subject_id": "26",
    "task_id": "motorseq"
  },
  "dummy_trs": 0,
  "dvars_nstd": 66.75509853835993,
  "dvars_std": 0.9870494212528473,
  "dvars_vstd": 0.9722731647608197,
  "efc": 0.5569986444307106,
  "fber": 211.03515625,
  "fd_mean": 0.11700852110281246,
  "fd_num": 38,
  "fd_perc": 8.636363636363637,
  "fwhm_avg": 2.562465,
  "fwhm_x": 2.41871,
  "fwhm_y": 2.67043,
  "fwhm_z": 2.598255,
  "gcor": 0.00342234,
  "gsr_x": -0.008319113403558731,
  "gsr_y": 0.056767918169498444,
  "provenance": {
    "md5sum": "d9d3efb8be859135637a2381d4b34d1b",
    "settings": {
      "fd_thres": 0.2,
      "testing": false
    },
    "software": "mriqc",
    "version": "23.0.1",
    "webapi_port": null,
    "webapi_url": "https://mriqc.nimh.nih.gov/api/v1"
  },
  "size_t": 440,
  "size_x": 104,
  "size_y": 104,
  "size_z": 44,
  "snr": 1.4601645166198496,
  "spacing_tr": 1.0,
  "spacing_x": 2.0,
  "spacing_y": 2.0,
  "spacing_z": 2.0,
  "summary_bg_k": 26.20392743762866,
  "summary_bg_mad": 4.943130989839623,
  "summary_bg_mean": 28.452566146850586,
  "summary_bg_median": 18.402271270751953,
  "summary_bg_n": 271636.0,
  "summary_bg_p05": 13.909090042114258,
  "summary_bg_p95": 82.35908508300781,
  "summary_bg_stdv": 29.658859252929688,
  "summary_fg_k": 5.530886363309195,
  "summary_fg_mad": 121.55989877960796,
  "summary_fg_mean": 327.64019775390625,
  "summary_fg_median": 271.3863525390625,
  "summary_fg_n": 132871.0,
  "summary_fg_p05": 148.2340850830078,
  "summary_fg_p95": 700.7238464355469,
  "summary_fg_stdv": 185.8594207763672,
  "tsnr": 17.613599566742778
}