{
  "aor": 0.0005079772727272727,
  "aqi": 0.026320443409090906,
  "bids_meta": {
    "dataset": "ds002776",
    "modality": "bold",
    "run_id": 8,
    "session_id": "03",
    "subject_id": "02",
    "task_id": "motorseq"
  },
  "dummy_trs": 0,
  "dvars_nstd": 102.48180491940768,
  "dvars_std": 1.0485266957403203,
  "dvars_vstd": 1.0060527123690204,
  "efc": 0.5537230942720586,
  "fber": 127.9256591796875,
  "fd_mean": 0.21522424113461142,
  "fd_num": 201,
  "fd_perc": 45.68181818181818,
  "fwhm_avg": 2.3862283333333334,
  "fwhm_x": 2.30968,
  "fwhm_y": 2.42032,
  "fwhm_z": 2.428685,
  "gcor": 0.00521126,
  "gsr_x": 0.003991062752902508,
  "gsr_y": 0.04994368925690651,
  "provenance": {
    "md5sum": "885b15c307f580306aaa0354664897e6",
    "settings": {
      "fd_thres": 0.2,
      "testing": false
    },
    "software": "mriqc",
    "version": "23.0.1",
    "webapi_port": null,
    "webapi_url": "https://mriqc.nimh.nih.gov/api/v1"
  },
  "size_t": 440,
  "size_x": 104,
  "size_y": 104,
  "size_z": 44,
  "snr": 1.8723295746562076,
  "spacing_tr": 1.0,
  "spacing_x": 2.0,
  "spacing_y": 2.0,
  "spacing_z": 2.0,
  "summary_bg_k": 32.7272984275183,
  "summary_bg_mad": 9.616695369187942,
  "summary_bg_mean": 28.425682067871094,
  "summary_bg_median": 24.43181800842285,
  "summary_bg_n": 305122.0,
  "summary_bg_p05": 12.72499942779541,
  "summary_bg_p95": 55.37272644042969,
  "summary_bg_stdv": 16.6043701171875,
  "summary_fg_k": 10.647730814109341,
  "summary_fg_mad": 90.77230725437677,
  "summary_fg_mean": 314.1419982910156,
  "summary_fg_median": 275.52044677734375,
  "summary_fg_n": 105600.0,
  "summary_fg_p05": 173.24533920288087,
  "summary_fg_p95": 595.218496704101,
  "summary_fg_stdv": 147.1531219482422,
  "tsnr": 14.59075578674674
}