{
  "aor": 0.0008963409090909091,
  "aqi": 0.022764915909090907,
  "bids_meta": {
    "dataset": "ds002776",
    "modality": "bold",
    "run_id": 3,
    "session_id": "01",
    "subject_id": "14",
    "task_id": "motorseq"
  },
  "dummy_trs": 0,
  "dvars_nstd": 74.22762331621867,
  "dvars_std": 1.0384763558769934,
  "dvars_vstd": 1.003794600820046,
  "efc": 0.5916913546434324,
  "fber": 257.6156921386719,
  "fd_mean": 0.27213957463726846,
  "fd_num": 239,
  "fd_perc": 54.31818181818182,
  "fwhm_avg": 2.471485,
  "fwhm_x": 2.36367,
  "fwhm_y": 2.573915,
  "fwhm_z": 2.47687,
  "gcor": 0.00629646,
  "gsr_x": 0.023916032165288925,
  "gsr_y": 0.03125520050525665,
  "provenance": {
    "md5sum": "605316ff4fdbc29ffad87869645fb93a",
    "settings": {
      "fd_thres": 0.2,
      "testing": false
    },
    "software": "mriqc",
    "version": "23.0.1",
    "webapi_port": null,
    "webapi_url": "https://mriqc.nimh.nih.gov/api/v1"
  },
  "size_t": 440,
  "size_x": 104,
  "size_y": 104,
  "size_z": 44,
  "snr": 2.5902269057823055,
  "spacing_tr": 1.0,
  "spacing_x": 2.0,
  "spacing_y": 2.0,
  "spacing_z": 2.0,
  "summary_bg_k": 59.437985557427076,
  "summary_bg_mad": 6.263993524834373,
  "summary_bg_mean": 27.3421630859375,
  "summary_bg_median": 18.674999237060547,
  "summary_bg_n": 277896.0,
  "summary_bg_p05": 12.91136360168457,
  "summary_bg_p95": 64.82783889770508,
  "summary_bg_stdv": 33.04804229736328,
  "summary_fg_k": 3.4437459505188874,
  "summary_fg_mad": 92.58178507492076,
  "summary_fg_mean": 328.04656982421875,
  "summary_fg_median": 304.2931823730469,
  "summary_fg_n": 128719.0,
  "summary_fg_p05": 196.154541015625,
  "summary_fg_p95": 564.7595458984374,
  "summary_fg_stdv": 117.47696685791016,
  "tsnr": 18.631810756400228
}