{
  "aor": 0.00037945454545454545,
  "aqi": 0.01885374159090909,
  "bids_meta": {
    "dataset": "ds002776",
    "modality": "bold",
    "run_id": 2,
    "session_id": "04",
    "subject_id": "14",
    "task_id": "motorseq"
  },
  "dummy_trs": 0,
  "dvars_nstd": 58.77154642665152,
  "dvars_std": 1.0034990973348523,
  "dvars_vstd": 0.9901397428473804,
  "efc": 0.5714462792285694,
  "fber": 332.4665222167969,
  "fd_mean": 0.08863914053687205,
  "fd_num": 3,
  "fd_perc": 0.6818181818181818,
  "fwhm_avg": 2.29424,
  "fwhm_x": 2.18493,
  "fwhm_y": 2.402585,
  "fwhm_z": 2.295205,
  "gcor": 0.0058938,
  "gsr_x": 0.02930799126625061,
  "gsr_y": 0.018156718462705612,
  "provenance": {
    "md5sum": "ef7dd722781ae1aa58759badc3af17cd",
    "settings": {
      "fd_thres": 0.2,
      "testing": false
    },
    "software": "mriqc",
    "version": "23.0.1",
    "webapi_port": null,
    "webapi_url": "https://mriqc.nimh.nih.gov/api/v1"
  },
  "size_t": 440,
  "size_x": 104,
  "size_y": 104,
  "size_z": 44,
  "snr": 2.6594500970755943,
  "spacing_tr": 1.0,
  "spacing_x": 2.0,
  "spacing_y": 2.0,
  "spacing_z": 2.0,
  "summary_bg_k": 60.10363128054548,
  "summary_bg_mad": 5.253130046849241,
  "summary_bg_mean": 24.68534278869629,
  "summary_bg_median": 16.72954559326172,
  "summary_bg_n": 287659.0,
  "summary_bg_p05": 11.856818199157715,
  "summary_bg_p95": 58.43863296508789,
  "summary_bg_stdv": 31.35098648071289,
  "summary_fg_k": 3.1452672868219054,
  "summary_fg_mad": 94.06605006294326,
  "summary_fg_mean": 332.07818603515625,
  "summary_fg_median": 308.276123046875,
  "summary_fg_n": 120834.0,
  "summary_fg_p05": 200.64089965820312,
  "summary_fg_p95": 559.2990478515621,
  "summary_fg_stdv": 115.91676330566406,
  "tsnr": 20.74872280994896
}