{
  "aor": 0.000866318181818182,
  "aqi": 0.028383594318181816,
  "bids_meta": {
    "dataset": "ds002776",
    "modality": "bold",
    "run_id": 1,
    "session_id": "02",
    "subject_id": "05",
    "task_id": "motorseq"
  },
  "dummy_trs": 0,
  "dvars_nstd": 71.52279431086563,
  "dvars_std": 1.0030669587471537,
  "dvars_vstd": 0.9862532140091109,
  "efc": 0.5282735438319789,
  "fber": 343.0099182128906,
  "fd_mean": 0.2413329927898933,
  "fd_num": 254,
  "fd_perc": 57.72727272727273,
  "fwhm_avg": 2.1065383754075593,
  "fwhm_x": 2.045665,
  "fwhm_y": 2.156285,
  "fwhm_z": 2.1176651262226778,
  "gcor": 0.00576678,
  "gsr_x": 0.006465170532464981,
  "gsr_y": 0.02047262340784073,
  "provenance": {
    "md5sum": "d4f96a16b17c1c7ce9642fddc7bdfab6",
    "settings": {
      "fd_thres": 0.2,
      "testing": false
    },
    "software": "mriqc",
    "version": "23.0.1",
    "webapi_port": null,
    "webapi_url": "https://mriqc.nimh.nih.gov/api/v1"
  },
  "size_t": 440,
  "size_x": 104,
  "size_y": 104,
  "size_z": 44,
  "snr": 2.323213644675344,
  "spacing_tr": 1.0,
  "spacing_x": 2.0,
  "spacing_y": 2.0,
  "spacing_z": 1.9999998807907104,
  "summary_bg_k": 100.27594507379389,
  "summary_bg_mad": 3.83791665312715,
  "summary_bg_mean": 20.02117156982422,
  "summary_bg_median": 15.949999809265137,
  "summary_bg_n": 305183.0,
  "summary_bg_p05": 12.18863582611084,
  "summary_bg_p95": 36.21818161010742,
  "summary_bg_stdv": 18.572097778320312,
  "summary_fg_k": 9.506414477345174,
  "summary_fg_mad": 86.87710564633672,
  "summary_fg_mean": 323.43121337890625,
  "summary_fg_median": 296.84320068359375,
  "summary_fg_n": 104860.0,
  "summary_fg_p05": 189.48090209960938,
  "summary_fg_p95": 554.3259185791013,
  "summary_fg_stdv": 127.77205657958984,
  "tsnr": 17.106381485587917
}